LICENSE.md
MANIFEST.in
README.rst
pyproject.toml
requirements.txt
setup.py
core_module_chemical_composition_app/__init__.py
core_module_chemical_composition_app/api.py
core_module_chemical_composition_app/settings.py
core_module_chemical_composition_app/urls.py
core_module_chemical_composition_app/views.py
core_module_chemical_composition_app.egg-info/PKG-INFO
core_module_chemical_composition_app.egg-info/SOURCES.txt
core_module_chemical_composition_app.egg-info/dependency_links.txt
core_module_chemical_composition_app.egg-info/requires.txt
core_module_chemical_composition_app.egg-info/top_level.txt
core_module_chemical_composition_app/static/core_module_chemical_composition_app/css/chemical_element_composition.css
core_module_chemical_composition_app/static/core_module_chemical_composition_app/js/chemical_element_composition.js
core_module_chemical_composition_app/static/core_module_chemical_composition_app/js/events.js
core_module_chemical_composition_app/templates/core_module_chemical_composition_app/chemical_composition.html
core_module_chemical_composition_app/templates/core_module_chemical_composition_app/edit_data.html
core_module_chemical_composition_app/templates/core_module_chemical_composition_app/render_data.html
tests/__init__.py
tests/test_settings.py